vulkan_platform_py/__init__.py
vulkan_platform_py-0.4.1.dist-info/LICENSE
vulkan_platform_py-0.4.1.dist-info/WHEEL
vulkan_platform_py-0.4.1.dist-info/METADATA
vulkan_platform_py-0.4.1.dist-info/RECORD
