Metadata-Version: 2.1
Name: vulkan-platform-py
Version: 0.4.1
Summary: 
Author: Rayan Hatout
Author-email: rayan.hatout@gmail.com
Requires-Python: >=3.10
Classifier: Programming Language :: Python :: 3
Classifier: Programming Language :: Python :: 3.10
Requires-Dist: GPUtil (>=1.4.0,<2.0.0)
Requires-Dist: dill (>=0.3.5,<0.4.0)
Requires-Dist: py-cpuinfo (>=8.0.0,<9.0.0)
Requires-Dist: pydantic (>=1.9.1,<2.0.0)
